gdMetriX/__init__.py
gdMetriX/boundary.py
gdMetriX/common.py
gdMetriX/crossing_data_types.py
gdMetriX/crossings.py
gdMetriX/datasets.py
gdMetriX/distribution.py
gdMetriX/edge_directions.py
gdMetriX/symmetry.py
gdMetriX/utils/avl_tree.py
gdMetriX/utils/edge_orientations.py
gdMetriX/utils/numeric.py
gdmetrix-0.0.4.dist-info/METADATA
gdmetrix-0.0.4.dist-info/WHEEL
gdmetrix-0.0.4.dist-info/licenses/LICENSE
gdmetrix-0.0.4.dist-info/RECORD
