Metadata-Version: 2.4
Name: gdMetriX
Version: 0.0.4
Summary: A small extension to networkX providing common metrics for graph drawing
Author: Martin Nöllenburg, Sebastian Röder, Markus Wallinger
License:                     GNU GENERAL PUBLIC LICENSE
License-File: LICENSE
Keywords: graph drawing,metrics,networks
Classifier: Development Status :: 3 - Alpha
Classifier: License :: OSI Approved :: GNU General Public License v3 (GPLv3)
Classifier: Operating System :: OS Independent
Classifier: Programming Language :: Python :: 3
Requires-Python: >=3.9
Requires-Dist: matplotlib>=3.10
Requires-Dist: networkx>=3.2
Requires-Dist: numpy>=1.24.4
Requires-Dist: osfclient>=0.0.5
Requires-Dist: scikit-image>=0.21.0
Requires-Dist: scipy>=1.10
Requires-Dist: shapely>=2.0.3
